README.md
setup.py
flextime/__init__.py
flextime/cli.py
flextime/interface.py
flextime/scheduler.py
flextime/tasktree.py
flextime/utils.py
flextime.egg-info/PKG-INFO
flextime.egg-info/SOURCES.txt
flextime.egg-info/dependency_links.txt
flextime.egg-info/entry_points.txt
flextime.egg-info/requires.txt
flextime.egg-info/top_level.txt