Metadata-Version: 1.1
Name: flextime
Version: 1.0
Summary: Hierarchical task management tool
Home-page: https://github.com/johncornish/flextime
Author: John Frederick Cornish IV
Author-email: johncornishthe4th@gmail.com
License: GPLv3
Download-URL: https://github.com/johncornish/flextime/archive/1.0.tar.gz
Platform: UNKNOWN
